README.md
setup.cfg
setup.py
src/WhaBot/WhaBot.py
src/WhaBot/__init__.py
src/WhaBot.egg-info/PKG-INFO
src/WhaBot.egg-info/SOURCES.txt
src/WhaBot.egg-info/dependency_links.txt
src/WhaBot.egg-info/requires.txt
src/WhaBot.egg-info/top_level.txt