Metadata-Version: 2.1
Name: WhaBot
Version: 1.1
Summary: The (not so official) WhatsApp automation framework!
Home-page: https://github.com/lanfran02/WhaBot
Author: Lanfran02
Author-email: joacolanfran+pypi@gmail.com
License: UNKNOWN
Project-URL: Bug Tracker, https://github.com/lanfran02/WhaBot/issues
Platform: UNKNOWN
Classifier: Programming Language :: Python :: 3
Classifier: License :: OSI Approved :: MIT License
Classifier: Operating System :: OS Independent
